cmp/__init__.py
cmp/info.py
cmp/parser.py
cmp/project.py
cmp/bidsappmanager/__init__.py
cmp/bidsappmanager/project.py
cmp/bidsappmanager/gui/__init__.py
cmp/bidsappmanager/gui/bidsapp.py
cmp/bidsappmanager/gui/config.py
cmp/bidsappmanager/gui/globals.py
cmp/bidsappmanager/gui/handlers.py
cmp/bidsappmanager/gui/principal.py
cmp/bidsappmanager/gui/qc.py
cmp/bidsappmanager/gui/traits.py
cmp/bidsappmanager/images/bidsapp.png
cmp/bidsappmanager/images/bidsapp_200x200.png
cmp/bidsappmanager/images/cmp.png
cmp/bidsappmanager/images/configurator.png
cmp/bidsappmanager/images/configurator_200x200.png
cmp/bidsappmanager/images/qualitycontrol.png
cmp/bidsappmanager/images/qualitycontrol_200x200.png
cmp/bidsappmanager/pipelines/__init__.py
cmp/bidsappmanager/pipelines/anatomical/__init__.py
cmp/bidsappmanager/pipelines/anatomical/anatomical.py
cmp/bidsappmanager/pipelines/anatomical/parcellation.png
cmp/bidsappmanager/pipelines/anatomical/segmentation.png
cmp/bidsappmanager/pipelines/diffusion/__init__.py
cmp/bidsappmanager/pipelines/diffusion/connectome.png
cmp/bidsappmanager/pipelines/diffusion/diffusion.png
cmp/bidsappmanager/pipelines/diffusion/diffusion.py
cmp/bidsappmanager/pipelines/diffusion/preprocessing.png
cmp/bidsappmanager/pipelines/diffusion/registration.png
cmp/bidsappmanager/pipelines/functional/__init__.py
cmp/bidsappmanager/pipelines/functional/connectome.png
cmp/bidsappmanager/pipelines/functional/eeg.py
cmp/bidsappmanager/pipelines/functional/eeg_connectome.png
cmp/bidsappmanager/pipelines/functional/eeg_preprocessing.png
cmp/bidsappmanager/pipelines/functional/eeg_sourceimaging.png
cmp/bidsappmanager/pipelines/functional/fMRI.py
cmp/bidsappmanager/pipelines/functional/functionalMRI.png
cmp/bidsappmanager/pipelines/functional/preprocessing.png
cmp/bidsappmanager/pipelines/functional/registration.png
cmp/bidsappmanager/stages/__init__.py
cmp/bidsappmanager/stages/connectome/__init__.py
cmp/bidsappmanager/stages/connectome/connectome.py
connectomemapper-3.2.0.dist-info/LICENSE
connectomemapper-3.2.0.dist-info/METADATA
connectomemapper-3.2.0.dist-info/WHEEL
connectomemapper-3.2.0.dist-info/entry_points.txt
connectomemapper-3.2.0.dist-info/top_level.txt
connectomemapper-3.2.0.dist-info/RECORD
