Metadata-Version: 2.1
Name: connectomemapper
Version: 3.2.0
Summary: Connectome Mapper 3: A Flexible and Open-Source Pipeline Software for Multiscale Multimodal Human Connectome Mapping
Home-page: https://github.com/connectomicslab/connectomemapper3
Author: Sebastien Tourbier
Author-email: sebastien.tourbier@alumni.epfl.ch
Maintainer: Connectomics Lab, CHUV
Maintainer-email: sebastien.tourbier@alumni.epfl.ch
License: BSD-3-Clause
Platform: UNKNOWN
Classifier: Development Status :: 5 - Production/Stable
Classifier: Intended Audience :: Science/Research
Classifier: Intended Audience :: Developers
Classifier: License :: OSI Approved
Classifier: Programming Language :: Python
Classifier: Topic :: Software Development
Classifier: Topic :: Scientific/Engineering
Classifier: Operating System :: Microsoft :: Windows
Classifier: Operating System :: POSIX
Classifier: Operating System :: Unix
Classifier: Operating System :: MacOS
Classifier: Programming Language :: Python :: 3.7
Requires-Python: >=3.7
License-File: LICENSE
Requires-Dist: codecarbon (==1.2.0)
Requires-Dist: dash-bootstrap-components (==0.13.1)
